{
  "assets": [
	{
	"token_id"	: "",
	"name"		: "Medium (M) WORLD in Somnium Space",
	"description"	: "Medium (M) WORLD with 200 MB available storage for uploading your own instances. Somnium Space Worlds are fully programmable and customizable independent Virtual Reality instances which can be created by using Somnium Space SDK. Each World is represented by a blockchain token (NFT) and lets you build, script and monetize entire worlds. Drop a world's blockchain token on a Somnium Space parcel to make a portal where everyone can enter the world it contains.",	
	"categories"	: ["world"],
	"tags"		: ["somniumspace","world"],
	"preview_img"	: "https://lh3.googleusercontent.com/l2Fk8HSQaT0hVZilj6kXrgoJ1XzRj38hsm3i4epROzA-ND_DCoKo3K1AnOioANlca1_eZ9qR8UXp4R1M1bS5hWVX=s0",	
	"image_link"    : "https://opensea.io/assets/0xf980759616a795b2d692a5c0a0f1bad651984bc1/32",		
	"images"	: [{}],
  	"button1" 	: {"title" : "Opensea", "link" : "https://opensea.io/assets/0xf980759616a795b2d692a5c0a0f1bad651984bc1/32"},  
	"button2" 	: {"title" : "", "link" : ""}		
	},	  
	{
	"token_id"	: "",
	"name"		: "Somnium WEB parcel 752",
	"description"	: "Experience 360째 NFT art made by Natural Warp.",	
	"categories"	: ["art"],
	"tags"		: ["naturalwarp","art","360"],
	"preview_img"	: "https://somniumtimes.com/wp-content/uploads/2021/03/parcel-752.jpg",
	"image_link"    : "https://somniumspace.com/parcel/752?elv=2.2",	
	"images"	: [{}],
  	"button1" 	: {"title" : "Somnium WEB", "link" : "https://somniumspace.com/parcel/752?elv=2.2"},
	"button2" 	: {"title" : "", "link" : ""}	
	},	  
	{
	"token_id"	: "",
	"name"		: "360 degree NFT Art",
	"description"	: "The first ever 360째 NFT ecosystem, featuring 360째 art pioneer Natural Warp",	
	"categories"	: ["art"],
	"tags"		: ["naturalwarp","art","360"],
	"preview_img"	: "https://somniumtimes.com/wp-content/uploads/2021/03/image-4.png",
	"image_link"    : "https://knownorigin.io/natural-warp",	
	"images"	: [{}],
  	"button1" 	: {"title" : "Known Origin", "link" : "https://knownorigin.io/natural-warp"},
	"button2" 	: {"title" : "Natural Warp 360째 gallery", "link" : "https://www.naturalwarp.com/360-gallery.html"}	
	}
  ]
}
